{
  "name": "rossta-c2rust/dice_game_probabilities/main.c",
  "start_line": 1,
  "end_line": 55,
  "kind": "unit",
  "spaces": [
    {
      "name": "ipow",
      "start_line": 7,
      "end_line": 12,
      "kind": "function",
      "spaces": [],
      "metrics": {
        "nargs": {
          "total_functions": 2.0,
          "total_closures": 0.0,
          "average_functions": 2.0,
          "average_closures": 0.0,
          "total": 2.0,
          "average": 2.0,
          "functions_min": 2.0,
          "functions_max": 2.0,
          "closures_min": 0.0,
          "closures_max": 0.0
        },
        "nexits": {
          "sum": 1.0,
          "average": 1.0,
          "min": 1.0,
          "max": 1.0
        },
        "cognitive": {
          "sum": 1.0,
          "average": 1.0,
          "min": 1.0,
          "max": 1.0
        },
        "cyclomatic": {
          "sum": 2.0,
          "average": 2.0,
          "min": 2.0,
          "max": 2.0
        },
        "halstead": {
          "n1": 10.0,
          "N1": 16.0,
          "n2": 8.0,
          "N2": 18.0,
          "length": 34.0,
          "estimated_program_length": 57.219280948873624,
          "purity_ratio": 1.6829200279080478,
          "vocabulary": 18.0,
          "volume": 141.7774500490386,
          "difficulty": 11.25,
          "level": 0.08888888888888889,
          "effort": 1594.9963130516844,
          "time": 88.61090628064913,
          "bugs": 0.04550424024284281
        },
        "loc": {
          "sloc": 6.0,
          "ploc": 6.0,
          "lloc": 4.0,
          "cloc": 0.0,
          "blank": 0.0,
          "sloc_average": 6.0,
          "ploc_average": 6.0,
          "lloc_average": 4.0,
          "cloc_average": 0.0,
          "blank_average": 0.0,
          "sloc_min": 6.0,
          "sloc_max": 6.0,
          "cloc_min": 0.0,
          "cloc_max": 0.0,
          "ploc_min": 6.0,
          "ploc_max": 6.0,
          "lloc_min": 4.0,
          "lloc_max": 4.0,
          "blank_min": 0.0,
          "blank_max": 0.0
        },
        "nom": {
          "functions": 1.0,
          "closures": 0.0,
          "functions_average": 1.0,
          "closures_average": 0.0,
          "total": 1.0,
          "average": 1.0,
          "functions_min": 1.0,
          "functions_max": 1.0,
          "closures_min": 0.0,
          "closures_max": 0.0
        },
        "mi": {
          "mi_original": 115.75135200850809,
          "mi_sei": 91.49668924566356,
          "mi_visual_studio": 67.69084912778251
        },
        "abc": {
          "assignments": 0.0,
          "branches": 0.0,
          "conditions": 0.0,
          "magnitude": 0.0,
          "assignments_average": 0.0,
          "branches_average": 0.0,
          "conditions_average": 0.0,
          "assignments_min": 0.0,
          "assignments_max": 0.0,
          "branches_min": 0.0,
          "branches_max": 0.0,
          "conditions_min": 0.0,
          "conditions_max": 0.0
        }
      }
    },
    {
      "name": "min",
      "start_line": 14,
      "end_line": 16,
      "kind": "function",
      "spaces": [],
      "metrics": {
        "nargs": {
          "total_functions": 2.0,
          "total_closures": 0.0,
          "average_functions": 2.0,
          "average_closures": 0.0,
          "total": 2.0,
          "average": 2.0,
          "functions_min": 2.0,
          "functions_max": 2.0,
          "closures_min": 0.0,
          "closures_max": 0.0
        },
        "nexits": {
          "sum": 1.0,
          "average": 1.0,
          "min": 1.0,
          "max": 1.0
        },
        "cognitive": {
          "sum": 0.0,
          "average": 0.0,
          "min": 0.0,
          "max": 0.0
        },
        "cyclomatic": {
          "sum": 2.0,
          "average": 2.0,
          "min": 2.0,
          "max": 2.0
        },
        "halstead": {
          "n1": 8.0,
          "N1": 9.0,
          "n2": 4.0,
          "N2": 10.0,
          "length": 19.0,
          "estimated_program_length": 32.0,
          "purity_ratio": 1.6842105263157894,
          "vocabulary": 12.0,
          "volume": 68.11428751370197,
          "difficulty": 10.0,
          "level": 0.1,
          "effort": 681.1428751370197,
          "time": 37.84127084094554,
          "bugs": 0.025805021430274792
        },
        "loc": {
          "sloc": 3.0,
          "ploc": 3.0,
          "lloc": 1.0,
          "cloc": 0.0,
          "blank": 0.0,
          "sloc_average": 3.0,
          "ploc_average": 3.0,
          "lloc_average": 1.0,
          "cloc_average": 0.0,
          "blank_average": 0.0,
          "sloc_min": 3.0,
          "sloc_max": 3.0,
          "cloc_min": 0.0,
          "cloc_max": 0.0,
          "ploc_min": 3.0,
          "ploc_max": 3.0,
          "lloc_min": 1.0,
          "lloc_max": 1.0,
          "blank_min": 0.0,
          "blank_max": 0.0
        },
        "nom": {
          "functions": 1.0,
          "closures": 0.0,
          "functions_average": 1.0,
          "closures_average": 0.0,
          "total": 1.0,
          "average": 1.0,
          "functions_min": 1.0,
          "functions_max": 1.0,
          "closures_min": 0.0,
          "closures_max": 0.0
        },
        "mi": {
          "mi_original": 130.79230855938675,
          "mi_sei": 113.1962026718426,
          "mi_visual_studio": 76.48673015168815
        },
        "abc": {
          "assignments": 0.0,
          "branches": 0.0,
          "conditions": 0.0,
          "magnitude": 0.0,
          "assignments_average": 0.0,
          "branches_average": 0.0,
          "conditions_average": 0.0,
          "assignments_min": 0.0,
          "assignments_max": 0.0,
          "branches_min": 0.0,
          "branches_max": 0.0,
          "conditions_min": 0.0,
          "conditions_max": 0.0
        }
      }
    },
    {
      "name": "throw_die",
      "start_line": 18,
      "end_line": 26,
      "kind": "function",
      "spaces": [],
      "metrics": {
        "nargs": {
          "total_functions": 4.0,
          "total_closures": 0.0,
          "average_functions": 4.0,
          "average_closures": 0.0,
          "total": 4.0,
          "average": 4.0,
          "functions_min": 4.0,
          "functions_max": 4.0,
          "closures_min": 0.0,
          "closures_max": 0.0
        },
        "nexits": {
          "sum": 1.0,
          "average": 1.0,
          "min": 1.0,
          "max": 1.0
        },
        "cognitive": {
          "sum": 2.0,
          "average": 2.0,
          "min": 2.0,
          "max": 2.0
        },
        "cyclomatic": {
          "sum": 3.0,
          "average": 3.0,
          "min": 3.0,
          "max": 3.0
        },
        "halstead": {
          "n1": 15.0,
          "N1": 31.0,
          "n2": 9.0,
          "N2": 27.0,
          "length": 58.0,
          "estimated_program_length": 87.13268394710859,
          "purity_ratio": 1.5022876542604928,
          "vocabulary": 24.0,
          "volume": 265.9278250418271,
          "difficulty": 22.5,
          "level": 0.044444444444444446,
          "effort": 5983.376063441109,
          "time": 332.4097813022838,
          "bugs": 0.10986084752711064
        },
        "loc": {
          "sloc": 9.0,
          "ploc": 8.0,
          "lloc": 5.0,
          "cloc": 0.0,
          "blank": 1.0,
          "sloc_average": 9.0,
          "ploc_average": 8.0,
          "lloc_average": 5.0,
          "cloc_average": 0.0,
          "blank_average": 1.0,
          "sloc_min": 9.0,
          "sloc_max": 9.0,
          "cloc_min": 0.0,
          "cloc_max": 0.0,
          "ploc_min": 8.0,
          "ploc_max": 8.0,
          "lloc_min": 5.0,
          "lloc_max": 5.0,
          "blank_min": 1.0,
          "blank_max": 1.0
        },
        "nom": {
          "functions": 1.0,
          "closures": 0.0,
          "functions_average": 1.0,
          "closures_average": 0.0,
          "total": 1.0,
          "average": 1.0,
          "functions_min": 1.0,
          "functions_max": 1.0,
          "closures_min": 0.0,
          "closures_max": 0.0
        },
        "mi": {
          "mi_original": 105.68219217197317,
          "mi_sei": 77.07178214298075,
          "mi_visual_studio": 61.80245156255741
        },
        "abc": {
          "assignments": 0.0,
          "branches": 0.0,
          "conditions": 0.0,
          "magnitude": 0.0,
          "assignments_average": 0.0,
          "branches_average": 0.0,
          "conditions_average": 0.0,
          "assignments_min": 0.0,
          "assignments_max": 0.0,
          "branches_min": 0.0,
          "branches_max": 0.0,
          "conditions_min": 0.0,
          "conditions_max": 0.0
        }
      }
    },
    {
      "name": "beating_probability",
      "start_line": 28,
      "end_line": 49,
      "kind": "function",
      "spaces": [],
      "metrics": {
        "nargs": {
          "total_functions": 4.0,
          "total_closures": 0.0,
          "average_functions": 4.0,
          "average_closures": 0.0,
          "total": 4.0,
          "average": 4.0,
          "functions_min": 4.0,
          "functions_max": 4.0,
          "closures_min": 0.0,
          "closures_max": 0.0
        },
        "nexits": {
          "sum": 1.0,
          "average": 1.0,
          "min": 1.0,
          "max": 1.0
        },
        "cognitive": {
          "sum": 5.0,
          "average": 5.0,
          "min": 5.0,
          "max": 5.0
        },
        "cyclomatic": {
          "sum": 5.0,
          "average": 5.0,
          "min": 5.0,
          "max": 5.0
        },
        "halstead": {
          "n1": 15.0,
          "N1": 90.0,
          "n2": 19.0,
          "N2": 83.0,
          "length": 173.0,
          "estimated_program_length": 139.3139816895559,
          "purity_ratio": 0.8052831311535024,
          "vocabulary": 34.0,
          "volume": 880.1310715363087,
          "difficulty": 32.76315789473684,
          "level": 0.030522088353413655,
          "effort": 28835.873264808008,
          "time": 1601.9929591560003,
          "bugs": 0.31344942970937395
        },
        "loc": {
          "sloc": 22.0,
          "ploc": 19.0,
          "lloc": 16.0,
          "cloc": 0.0,
          "blank": 3.0,
          "sloc_average": 22.0,
          "ploc_average": 19.0,
          "lloc_average": 16.0,
          "cloc_average": 0.0,
          "blank_average": 3.0,
          "sloc_min": 22.0,
          "sloc_max": 22.0,
          "cloc_min": 0.0,
          "cloc_max": 0.0,
          "ploc_min": 19.0,
          "ploc_max": 19.0,
          "lloc_min": 16.0,
          "lloc_max": 16.0,
          "blank_min": 3.0,
          "blank_max": 3.0
        },
        "nom": {
          "functions": 1.0,
          "closures": 0.0,
          "functions_average": 1.0,
          "closures_average": 0.0,
          "total": 1.0,
          "average": 1.0,
          "functions_min": 1.0,
          "functions_max": 1.0,
          "closures_min": 0.0,
          "closures_max": 0.0
        },
        "mi": {
          "mi_original": 84.51874388079011,
          "mi_sei": 46.74301996398991,
          "mi_visual_studio": 49.426166012157964
        },
        "abc": {
          "assignments": 0.0,
          "branches": 0.0,
          "conditions": 0.0,
          "magnitude": 0.0,
          "assignments_average": 0.0,
          "branches_average": 0.0,
          "conditions_average": 0.0,
          "assignments_min": 0.0,
          "assignments_max": 0.0,
          "branches_min": 0.0,
          "branches_max": 0.0,
          "conditions_min": 0.0,
          "conditions_max": 0.0
        }
      }
    },
    {
      "name": "main",
      "start_line": 51,
      "end_line": 55,
      "kind": "function",
      "spaces": [],
      "metrics": {
        "nargs": {
          "total_functions": 0.0,
          "total_closures": 0.0,
          "average_functions": 0.0,
          "average_closures": 0.0,
          "total": 0.0,
          "average": 0.0,
          "functions_min": 0.0,
          "functions_max": 0.0,
          "closures_min": 0.0,
          "closures_max": 0.0
        },
        "nexits": {
          "sum": 1.0,
          "average": 1.0,
          "min": 1.0,
          "max": 1.0
        },
        "cognitive": {
          "sum": 0.0,
          "average": 0.0,
          "min": 0.0,
          "max": 0.0
        },
        "cyclomatic": {
          "sum": 1.0,
          "average": 1.0,
          "min": 1.0,
          "max": 1.0
        },
        "halstead": {
          "n1": 6.0,
          "N1": 19.0,
          "n2": 11.0,
          "N2": 16.0,
          "length": 35.0,
          "estimated_program_length": 53.5635228093372,
          "purity_ratio": 1.5303863659810628,
          "vocabulary": 17.0,
          "volume": 143.06119944376186,
          "difficulty": 4.363636363636363,
          "level": 0.22916666666666669,
          "effort": 624.2670521182336,
          "time": 34.68150289545742,
          "bugs": 0.024347760514342266
        },
        "loc": {
          "sloc": 5.0,
          "ploc": 5.0,
          "lloc": 3.0,
          "cloc": 0.0,
          "blank": 0.0,
          "sloc_average": 5.0,
          "ploc_average": 5.0,
          "lloc_average": 3.0,
          "cloc_average": 0.0,
          "blank_average": 0.0,
          "sloc_min": 5.0,
          "sloc_max": 5.0,
          "cloc_min": 0.0,
          "cloc_max": 0.0,
          "ploc_min": 5.0,
          "ploc_max": 5.0,
          "lloc_min": 3.0,
          "lloc_max": 3.0,
          "blank_min": 0.0,
          "blank_max": 0.0
        },
        "nom": {
          "functions": 1.0,
          "closures": 0.0,
          "functions_average": 1.0,
          "closures_average": 0.0,
          "total": 1.0,
          "average": 1.0,
          "functions_min": 1.0,
          "functions_max": 1.0,
          "closures_min": 0.0,
          "closures_max": 0.0
        },
        "mi": {
          "mi_original": 118.88808878296913,
          "mi_sei": 95.92022397534808,
          "mi_visual_studio": 69.5251981186954
        },
        "abc": {
          "assignments": 0.0,
          "branches": 0.0,
          "conditions": 0.0,
          "magnitude": 0.0,
          "assignments_average": 0.0,
          "branches_average": 0.0,
          "conditions_average": 0.0,
          "assignments_min": 0.0,
          "assignments_max": 0.0,
          "branches_min": 0.0,
          "branches_max": 0.0,
          "conditions_min": 0.0,
          "conditions_max": 0.0
        }
      }
    }
  ],
  "metrics": {
    "nargs": {
      "total_functions": 12.0,
      "total_closures": 0.0,
      "average_functions": 2.4,
      "average_closures": 0.0,
      "total": 12.0,
      "average": 2.4,
      "functions_min": 0.0,
      "functions_max": 4.0,
      "closures_min": 0.0,
      "closures_max": 0.0
    },
    "nexits": {
      "sum": 0.0,
      "average": 1.0,
      "min": 0.0,
      "max": 1.0
    },
    "cognitive": {
      "sum": 8.0,
      "average": 1.6,
      "min": 0.0,
      "max": 5.0
    },
    "cyclomatic": {
      "sum": 14.0,
      "average": 2.3333333333333335,
      "min": 1.0,
      "max": 5.0
    },
    "halstead": {
      "n1": 22.0,
      "N1": 169.0,
      "n2": 36.0,
      "N2": 156.0,
      "length": 325.0,
      "estimated_program_length": 284.22479566194374,
      "purity_ratio": 0.8745378328059807,
      "vocabulary": 58.0,
      "volume": 1903.843823416461,
      "difficulty": 47.666666666666664,
      "level": 0.02097902097902098,
      "effort": 90749.88891618463,
      "time": 5041.660495343591,
      "bugs": 0.673146326371193
    },
    "loc": {
      "sloc": 55.0,
      "ploc": 45.0,
      "lloc": 29.0,
      "cloc": 0.0,
      "blank": 10.0,
      "sloc_average": 9.166666666666666,
      "ploc_average": 7.5,
      "lloc_average": 4.833333333333333,
      "cloc_average": 0.0,
      "blank_average": 1.6666666666666667,
      "sloc_min": 3.0,
      "sloc_max": 22.0,
      "cloc_min": 0.0,
      "cloc_max": 0.0,
      "ploc_min": 3.0,
      "ploc_max": 19.0,
      "lloc_min": 1.0,
      "lloc_max": 16.0,
      "blank_min": 0.0,
      "blank_max": 3.0
    },
    "nom": {
      "functions": 5.0,
      "closures": 0.0,
      "functions_average": 0.8333333333333334,
      "closures_average": 0.0,
      "total": 5.0,
      "average": 0.8333333333333334,
      "functions_min": 0.0,
      "functions_max": 1.0,
      "closures_min": 0.0,
      "closures_max": 0.0
    },
    "mi": {
      "mi_original": 63.592725429587546,
      "mi_sei": 17.46953565352912,
      "mi_visual_studio": 37.188728321396226
    },
    "abc": {
      "assignments": 0.0,
      "branches": 0.0,
      "conditions": 0.0,
      "magnitude": 0.0,
      "assignments_average": 0.0,
      "branches_average": 0.0,
      "conditions_average": 0.0,
      "assignments_min": 0.0,
      "assignments_max": 0.0,
      "branches_min": 0.0,
      "branches_max": 0.0,
      "conditions_min": 0.0,
      "conditions_max": 0.0
    }
  }
}