{
  "name": "rossta-c2rust/repeat_a_string/main.c",
  "start_line": 1,
  "end_line": 22,
  "kind": "unit",
  "spaces": [
    {
      "name": "string_repeat",
      "start_line": 5,
      "end_line": 15,
      "kind": "function",
      "spaces": [],
      "metrics": {
        "nargs": {
          "total_functions": 0.0,
          "total_closures": 0.0,
          "average_functions": 0.0,
          "average_closures": 0.0,
          "total": 0.0,
          "average": 0.0,
          "functions_min": 0.0,
          "functions_max": 0.0,
          "closures_min": 0.0,
          "closures_max": 0.0
        },
        "nexits": {
          "sum": 1.0,
          "average": 1.0,
          "min": 1.0,
          "max": 1.0
        },
        "cognitive": {
          "sum": 1.0,
          "average": 1.0,
          "min": 1.0,
          "max": 1.0
        },
        "cyclomatic": {
          "sum": 2.0,
          "average": 2.0,
          "min": 2.0,
          "max": 2.0
        },
        "halstead": {
          "n1": 13.0,
          "N1": 45.0,
          "n2": 12.0,
          "N2": 28.0,
          "length": 73.0,
          "estimated_program_length": 91.12526634448807,
          "purity_ratio": 1.2482913197875078,
          "vocabulary": 25.0,
          "volume": 339.0015018535549,
          "difficulty": 15.166666666666666,
          "level": 0.06593406593406594,
          "effort": 5141.5227781122485,
          "time": 285.64015433956934,
          "bugs": 0.09929786741155107
        },
        "loc": {
          "sloc": 11.0,
          "ploc": 10.0,
          "lloc": 8.0,
          "cloc": 0.0,
          "blank": 1.0,
          "sloc_average": 11.0,
          "ploc_average": 10.0,
          "lloc_average": 8.0,
          "cloc_average": 0.0,
          "blank_average": 1.0,
          "sloc_min": 11.0,
          "sloc_max": 11.0,
          "cloc_min": 0.0,
          "cloc_max": 0.0,
          "ploc_min": 10.0,
          "ploc_max": 10.0,
          "lloc_min": 8.0,
          "lloc_max": 8.0,
          "blank_min": 1.0,
          "blank_max": 1.0
        },
        "nom": {
          "functions": 1.0,
          "closures": 0.0,
          "functions_average": 1.0,
          "closures_average": 0.0,
          "total": 1.0,
          "average": 1.0,
          "functions_min": 1.0,
          "functions_max": 1.0,
          "closures_min": 0.0,
          "closures_max": 0.0
        },
        "mi": {
          "mi_original": 101.39887298505741,
          "mi_sei": 70.79043893406839,
          "mi_visual_studio": 59.29758654096924
        },
        "abc": {
          "assignments": 0.0,
          "branches": 0.0,
          "conditions": 0.0,
          "magnitude": 0.0,
          "assignments_average": 0.0,
          "branches_average": 0.0,
          "conditions_average": 0.0,
          "assignments_min": 0.0,
          "assignments_max": 0.0,
          "branches_min": 0.0,
          "branches_max": 0.0,
          "conditions_min": 0.0,
          "conditions_max": 0.0
        }
      }
    },
    {
      "name": "main",
      "start_line": 17,
      "end_line": 22,
      "kind": "function",
      "spaces": [],
      "metrics": {
        "nargs": {
          "total_functions": 0.0,
          "total_closures": 0.0,
          "average_functions": 0.0,
          "average_closures": 0.0,
          "total": 0.0,
          "average": 0.0,
          "functions_min": 0.0,
          "functions_max": 0.0,
          "closures_min": 0.0,
          "closures_max": 0.0
        },
        "nexits": {
          "sum": 1.0,
          "average": 1.0,
          "min": 1.0,
          "max": 1.0
        },
        "cognitive": {
          "sum": 0.0,
          "average": 0.0,
          "min": 0.0,
          "max": 0.0
        },
        "cyclomatic": {
          "sum": 1.0,
          "average": 1.0,
          "min": 1.0,
          "max": 1.0
        },
        "halstead": {
          "n1": 8.0,
          "N1": 15.0,
          "n2": 8.0,
          "N2": 10.0,
          "length": 25.0,
          "estimated_program_length": 48.0,
          "purity_ratio": 1.92,
          "vocabulary": 16.0,
          "volume": 100.0,
          "difficulty": 5.0,
          "level": 0.2,
          "effort": 500.0,
          "time": 27.77777777777778,
          "bugs": 0.020998684164914547
        },
        "loc": {
          "sloc": 6.0,
          "ploc": 6.0,
          "lloc": 4.0,
          "cloc": 0.0,
          "blank": 0.0,
          "sloc_average": 6.0,
          "ploc_average": 6.0,
          "lloc_average": 4.0,
          "cloc_average": 0.0,
          "blank_average": 0.0,
          "sloc_min": 6.0,
          "sloc_max": 6.0,
          "cloc_min": 0.0,
          "cloc_max": 0.0,
          "ploc_min": 6.0,
          "ploc_max": 6.0,
          "lloc_min": 4.0,
          "lloc_max": 4.0,
          "blank_min": 0.0,
          "blank_max": 0.0
        },
        "nom": {
          "functions": 1.0,
          "closures": 0.0,
          "functions_average": 1.0,
          "closures_average": 0.0,
          "total": 1.0,
          "average": 1.0,
          "functions_min": 1.0,
          "functions_max": 1.0,
          "closures_min": 0.0,
          "closures_max": 0.0
        },
        "mi": {
          "mi_original": 117.79661163136743,
          "mi_sei": 94.34555530148873,
          "mi_visual_studio": 68.88690738676458
        },
        "abc": {
          "assignments": 0.0,
          "branches": 0.0,
          "conditions": 0.0,
          "magnitude": 0.0,
          "assignments_average": 0.0,
          "branches_average": 0.0,
          "conditions_average": 0.0,
          "assignments_min": 0.0,
          "assignments_max": 0.0,
          "branches_min": 0.0,
          "branches_max": 0.0,
          "conditions_min": 0.0,
          "conditions_max": 0.0
        }
      }
    }
  ],
  "metrics": {
    "nargs": {
      "total_functions": 0.0,
      "total_closures": 0.0,
      "average_functions": 0.0,
      "average_closures": 0.0,
      "total": 0.0,
      "average": 0.0,
      "functions_min": 0.0,
      "functions_max": 0.0,
      "closures_min": 0.0,
      "closures_max": 0.0
    },
    "nexits": {
      "sum": 0.0,
      "average": 1.0,
      "min": 0.0,
      "max": 1.0
    },
    "cognitive": {
      "sum": 1.0,
      "average": 0.5,
      "min": 0.0,
      "max": 1.0
    },
    "cyclomatic": {
      "sum": 4.0,
      "average": 1.3333333333333333,
      "min": 1.0,
      "max": 2.0
    },
    "halstead": {
      "n1": 13.0,
      "N1": 60.0,
      "n2": 18.0,
      "N2": 38.0,
      "length": 98.0,
      "estimated_program_length": 123.1643663617958,
      "purity_ratio": 1.256779248589753,
      "vocabulary": 31.0,
      "volume": 485.5112384179137,
      "difficulty": 13.722222222222221,
      "level": 0.07287449392712551,
      "effort": 6662.293104956927,
      "time": 370.1273947198293,
      "bugs": 0.11802152867427484
    },
    "loc": {
      "sloc": 22.0,
      "ploc": 19.0,
      "lloc": 12.0,
      "cloc": 0.0,
      "blank": 3.0,
      "sloc_average": 7.333333333333333,
      "ploc_average": 6.333333333333333,
      "lloc_average": 4.0,
      "cloc_average": 0.0,
      "blank_average": 1.0,
      "sloc_min": 6.0,
      "sloc_max": 11.0,
      "cloc_min": 0.0,
      "cloc_max": 0.0,
      "ploc_min": 6.0,
      "ploc_max": 10.0,
      "lloc_min": 4.0,
      "lloc_max": 8.0,
      "blank_min": 0.0,
      "blank_max": 1.0
    },
    "nom": {
      "functions": 2.0,
      "closures": 0.0,
      "functions_average": 0.6666666666666666,
      "closures_average": 0.0,
      "total": 2.0,
      "average": 0.6666666666666666,
      "functions_min": 0.0,
      "functions_max": 1.0,
      "closures_min": 0.0,
      "closures_max": 0.0
    },
    "mi": {
      "mi_original": 87.84205959050072,
      "mi_sei": 51.43573119829328,
      "mi_visual_studio": 51.36962549152089
    },
    "abc": {
      "assignments": 0.0,
      "branches": 0.0,
      "conditions": 0.0,
      "magnitude": 0.0,
      "assignments_average": 0.0,
      "branches_average": 0.0,
      "conditions_average": 0.0,
      "assignments_min": 0.0,
      "assignments_max": 0.0,
      "branches_min": 0.0,
      "branches_max": 0.0,
      "conditions_min": 0.0,
      "conditions_max": 0.0
    }
  }
}